[
  {
    "timestamp": "2026-03-24T15:00-04:00",
    "title": "Asia Late Session: Markets Consolidate After Midday Volatility",
    "commentary": "Asian trading winds down with modest losses as oil's midday surge fades\u2014Nikkei -0.3%, HSI -0.6% after earlier Iran-driven swings. WTI stabilizes near $91 as traders digest the ceasefire pause timeline; Brent holds $102. Gold drifts at $4,425 as safe-haven flows pause; crypto quiet with BTC at $70K, ETH $2,135. European open will test whether Tuesday's defensive rotation holds or tech weakness spreads. Iran's 48-hour response window remains the single variable driving all asset class correlations.",
    "movers": [
      {
        "symbol": "Gold",
        "price": "4,425",
        "change": "+0.4%"
      },
      {
        "symbol": "Silver",
        "price": "70.20",
        "change": "+0.2%"
      },
      {
        "symbol": "Oil (WTI)",
        "price": "91.20",
        "change": "+3.5%"
      },
      {
        "symbol": "Oil (Brent)",
        "price": "102.50",
        "change": "+2.8%"
      },
      {
        "symbol": "S&P 500",
        "price": "6,575",
        "change": "-0.1% (futures)"
      },
      {
        "symbol": "Nasdaq",
        "price": "21,820",
        "change": "-0.5% (futures)"
      },
      {
        "symbol": "Dow Jones",
        "price": "46,240",
        "change": "+0.1% (futures)"
      },
      {
        "symbol": "Bitcoin",
        "price": "70,000",
        "change": "-1.3%"
      },
      {
        "symbol": "Ethereum",
        "price": "2,135",
        "change": "-0.8%"
      },
      {
        "symbol": "USD Index",
        "price": "99.35",
        "change": "+0.2%"
      }
    ]
  },
  {
    "timestamp": "2026-03-24T12:00-04:00",
    "title": "Midday Update: Oil Surges 4% as Dow Turns Green, Tech Lags",
    "commentary": "WTI crude punches to $91.70 (+4.0%) as Iran war jitters return\u2014Brent comfortably above $100 at $103.08 keeps energy sector bid. Dow edges positive (+0.1%) on defensive rotation while Nasdaq (-0.5%) underperforms as growth stocks face profit-taking. Gold holds $4,428 (+0.5%), USD steady at 99.38 as traders await next Iran headline. BTC dips below $70K to $69,917 (-1.4%), ETH -0.9% at $2,133\u2014crypto tracking macro risk, not leading.",
    "movers": [
      {
        "symbol": "Gold",
        "price": "4,428",
        "change": "+0.47%"
      },
      {
        "symbol": "Silver",
        "price": "70.34",
        "change": "+0.23%"
      },
      {
        "symbol": "Oil (WTI)",
        "price": "91.70",
        "change": "+4.05%"
      },
      {
        "symbol": "Oil (Brent)",
        "price": "103.08",
        "change": "+3.14%"
      },
      {
        "symbol": "S&P 500",
        "price": "6,578",
        "change": "-0.05%"
      },
      {
        "symbol": "Nasdaq",
        "price": "21,847",
        "change": "-0.46%"
      },
      {
        "symbol": "Dow Jones",
        "price": "46,253",
        "change": "+0.10%"
      },
      {
        "symbol": "Bitcoin",
        "price": "69,917",
        "change": "-1.40%"
      },
      {
        "symbol": "Ethereum",
        "price": "2,133",
        "change": "-0.87%"
      },
      {
        "symbol": "USD Index",
        "price": "99.38",
        "change": "+0.30%"
      }
    ]
  },
  {
    "timestamp": "2026-03-24T11:00-04:00",
    "title": "Midday Update: Oil Spikes 4.4% as Tech Drags, Dow Outperforms",
    "commentary": "Oil punches back above $92 (+4.4%) in the session's biggest mover, reigniting supply-side jitters as Iran's strike-pause deadline approaches\u2014Brent likely above $100 again. Nasdaq underperforms at -0.69% as growth names face renewed pressure; Dow ekes out gains at +0.17% on defensive rotation. Precious metals flat (gold $4,405, silver $69.67) as traders await clarity on geopolitical front. BTC steady at $69,899, ETH at $2,137\u2014crypto content to track macro rather than lead.",
    "movers": [
      {
        "symbol": "Gold",
        "price": "4,405",
        "change": "-0.05%"
      },
      {
        "symbol": "Silver",
        "price": "69.67",
        "change": "+0.45%"
      },
      {
        "symbol": "Oil (WTI)",
        "price": "92.01",
        "change": "+4.40%"
      },
      {
        "symbol": "S&P 500",
        "price": "6,577",
        "change": "-0.06%"
      },
      {
        "symbol": "Nasdaq",
        "price": "21,795",
        "change": "-0.69%"
      },
      {
        "symbol": "Dow Jones",
        "price": "46,286",
        "change": "+0.17%"
      },
      {
        "symbol": "Bitcoin",
        "price": "69,899",
        "change": "~flat"
      },
      {
        "symbol": "Ethereum",
        "price": "2,137",
        "change": "~flat"
      },
      {
        "symbol": "USD Index",
        "price": "~99",
        "change": "~flat"
      }
    ]
  },
  {
    "timestamp": "2026-03-24T10:00-04:00",
    "title": "Tuesday Trading: Stocks Retreat as Oil Rebounds, War Uncertainty Lingers",
    "commentary": "Wall Street gives back Monday's de-escalation rally as Brent crude punches through $100 and Iran war uncertainty returns to the fore\u2014Dow -0.6% at 45,921, Nasdaq -0.6% at 24,036. Asia outperforms with HSI +2.8%, Nikkei +1.4% on spillover optimism that hasn't crossed the Pacific. Euro zone PMIs flash stagflation warnings as energy crunch bites; Treasury yields climb. Bitcoin slides to $70,079 (-1.2%), Ethereum -0.6% at $2,139 as risk appetite sours. One-variable market: it's all Iran now.",
    "movers": [
      {
        "symbol": "Gold",
        "price": "4,420",
        "change": "+0.5%"
      },
      {
        "symbol": "Silver",
        "price": "69.30",
        "change": "+0.4%"
      },
      {
        "symbol": "Oil (WTI)",
        "price": "92.50",
        "change": "+4.2%"
      },
      {
        "symbol": "Oil (Brent)",
        "price": "100.20",
        "change": "+0.4%"
      },
      {
        "symbol": "S&P 500",
        "price": "6,092",
        "change": "-0.6%"
      },
      {
        "symbol": "Nasdaq",
        "price": "24,036",
        "change": "-0.63%"
      },
      {
        "symbol": "Dow Jones",
        "price": "45,921",
        "change": "-0.62%"
      },
      {
        "symbol": "Bitcoin",
        "price": "70,079",
        "change": "-1.17%"
      },
      {
        "symbol": "Ethereum",
        "price": "2,139",
        "change": "-0.63%"
      },
      {
        "symbol": "USD Index",
        "price": "99.30",
        "change": "+0.2%"
      }
    ]
  },
  {
    "timestamp": "2026-03-23T20:00-04:00",
    "title": "Asia-Pacific Open: De-escalation Rally Extends into New Week",
    "commentary": "Risk-on momentum carries into Asia session as Trump-Iran ceasefire talks hold\u2014S&P futures steady at 6,590 (+1.3% from Monday close) while oil extends two-day collapse with WTI at $88.78, down 35% from crisis highs. Gold continues safe-haven unwind at $4,399 (-2%), capping its steepest weekly correction since 2013. Crypto catches the tailwind: BTC +3.7% at $70,682, ETH +4.4% at $2,154 as risk appetite returns. Dollar weakens to 99.12 on improved sentiment; all eyes on whether Iran's 48-hour response deadline passes without incident.",
    "movers": [
      {
        "symbol": "Gold",
        "price": "4,399",
        "change": "-2.0%"
      },
      {
        "symbol": "Silver",
        "price": "69.04",
        "change": "+2.1%"
      },
      {
        "symbol": "Oil (WTI)",
        "price": "88.78",
        "change": "-0.9%"
      },
      {
        "symbol": "Oil (Brent)",
        "price": "99.82",
        "change": "+1.2%"
      },
      {
        "symbol": "S&P 500",
        "price": "6,590",
        "change": "+1.3%"
      },
      {
        "symbol": "Nasdaq",
        "price": "21,993",
        "change": "flat (futures)"
      },
      {
        "symbol": "Dow Jones",
        "price": "46,400",
        "change": "flat (futures)"
      },
      {
        "symbol": "Bitcoin",
        "price": "70,682",
        "change": "+3.7%"
      },
      {
        "symbol": "Ethereum",
        "price": "2,154",
        "change": "+4.4%"
      },
      {
        "symbol": "USD Index",
        "price": "99.12",
        "change": "-0.5%"
      }
    ]
  },
  {
    "timestamp": "2026-03-23T19:00-04:00",
    "title": "Overnight Futures: Oil Collapses as Iran De-escalation Continues",
    "commentary": "WTI craters 11% to $87.30, Brent -12% to $98.60 as Trump's five-day strike pause continues to defuse supply fears\u2014biggest multi-day crude unwind since 2020. Gold slips 0.9% to $4,448 as safe-haven premium bleeds out; crypto rides lingering risk-on momentum with BTC +3.6% at $71,050, ETH +4.8% at $2,169. Fed's Goolsbee warns on inflation in 'fraught but intense' climate\u2014markets watching whether de-escalation holds or Iran ultimatum reignites volatility.",
    "movers": [
      {
        "symbol": "Gold",
        "price": "4,448",
        "change": "-0.9%"
      },
      {
        "symbol": "Silver",
        "price": "69.50",
        "change": "flat"
      },
      {
        "symbol": "Oil (WTI)",
        "price": "87.30",
        "change": "-11.1%"
      },
      {
        "symbol": "Oil (Brent)",
        "price": "98.60",
        "change": "-12.1%"
      },
      {
        "symbol": "S&P 500",
        "price": "6,605",
        "change": "flat (futures)"
      },
      {
        "symbol": "Nasdaq",
        "price": "21,993",
        "change": "flat (futures)"
      },
      {
        "symbol": "Dow Jones",
        "price": "46,400",
        "change": "flat (futures)"
      },
      {
        "symbol": "Bitcoin",
        "price": "71,050",
        "change": "+3.6%"
      },
      {
        "symbol": "Ethereum",
        "price": "2,169",
        "change": "+4.8%"
      },
      {
        "symbol": "USD Index",
        "price": "99.24",
        "change": "flat"
      }
    ]
  },
  {
    "timestamp": "2026-03-23T16:00-04:00",
    "title": "US Close: Wall Street Caps Historic Rally, Iran Breakthrough Lifts Sentiment",
    "commentary": "S&P 500 closes at 6,605, up 1.5% in one of the sharpest single-day reversals this year as Trump-Iran diplomacy halts military escalation. Dow finishes +900 points at 46,416, Nasdaq +1.9% to 21,993. Oil craters 9% to $89.30 as strike pause defuses supply fears\u2014biggest drop since 2022. Gold unwind continues with spot down 3.4% to $4,418; crypto rides risk-on wave with BTC at $71,100. Week ahead: All eyes on Iran's 48-hour ultimatum response. Fed speak resumes Tuesday.",
    "movers": [
      {
        "symbol": "Gold",
        "price": "4,418",
        "change": "-3.4%"
      },
      {
        "symbol": "Silver",
        "price": "69.50",
        "change": "-0.3%"
      },
      {
        "symbol": "Oil (WTI)",
        "price": "89.30",
        "change": "-9.1%"
      },
      {
        "symbol": "S&P 500",
        "price": "6,605",
        "change": "+1.5%"
      },
      {
        "symbol": "Nasdaq",
        "price": "21,993",
        "change": "+1.9%"
      },
      {
        "symbol": "Dow Jones",
        "price": "46,400",
        "change": "+1.8%"
      },
      {
        "symbol": "Bitcoin",
        "price": "71,104",
        "change": "+2.1%"
      },
      {
        "symbol": "Ethereum",
        "price": "2,154",
        "change": "+1.5%"
      },
      {
        "symbol": "USD Index",
        "price": "99.24",
        "change": "-0.4%"
      }
    ]
  },
  {
    "timestamp": "2026-03-23T10:00-04:00",
    "title": "US Morning: Risk-On Surge as Trump-Iran Talks Signal De-escalation",
    "commentary": "Dow explodes 900+ points (+2%) after Trump tells CNBC 'productive' Iran talks are underway, triggering the sharpest intraday rally in months. Oil collapses 9.6% to $88.76 as Trump pauses strikes on Iranian energy infrastructure for five days\u2014biggest single-day crude drop since 2022. Safe-haven unwind accelerates: gold dumps 2.9% to $4,445, silver -1% to $69. Crypto catches the risk-on bid with BTC/ETH climbing alongside equities. Traders now pricing de-escalation, but 48-hour Hormuz ultimatum still looms.",
    "movers": [
      {
        "symbol": "Gold",
        "price": "4,445",
        "change": "-2.85%"
      },
      {
        "symbol": "Silver",
        "price": "68.99",
        "change": "-0.97%"
      },
      {
        "symbol": "Oil (WTI)",
        "price": "88.76",
        "change": "-9.64%"
      },
      {
        "symbol": "S&P 500",
        "price": "6,626",
        "change": "+1.84%"
      },
      {
        "symbol": "Nasdaq",
        "price": "22,103",
        "change": "+2.10%"
      },
      {
        "symbol": "Dow Jones",
        "price": "46,494",
        "change": "+2.01%"
      },
      {
        "symbol": "Bitcoin",
        "price": "72,500",
        "change": "+2.5%"
      },
      {
        "symbol": "Ethereum",
        "price": "2,210",
        "change": "+3.3%"
      },
      {
        "symbol": "USD Index",
        "price": "99.20",
        "change": "-0.2%"
      }
    ]
  },
  {
    "timestamp": "2026-03-23T09:01-04:00",
    "title": "US Pre-Market: Futures Surge on Iran Diplomacy Breakthrough",
    "commentary": "Dow futures explode +1,000 points after Trump announces \"productive\" talks with Iran, postponing military strike\u2014biggest pre-market jump in months erases Friday's war-panic selloff. Asia closes bloodied (Nikkei -3.5%, HSI -3.5%) before the diplomatic pivot; BTC rebounds 4.2% to $70,719 as risk appetite returns. Gold extends nine-session slide as safe-haven unwind accelerates; oil pulls back from crisis highs. Volatility remains elevated as traders await confirmation of de-escalation.",
    "movers": [
      {
        "symbol": "Gold",
        "price": "4,450",
        "change": "-1.0%"
      },
      {
        "symbol": "Silver",
        "price": "33.20",
        "change": "-1.2%"
      },
      {
        "symbol": "Oil (WTI)",
        "price": "95.50",
        "change": "-2.0%"
      },
      {
        "symbol": "S&P 500",
        "price": "6,506",
        "change": "flat"
      },
      {
        "symbol": "Nasdaq",
        "price": "21,850",
        "change": "flat"
      },
      {
        "symbol": "Dow Jones",
        "price": "45,577",
        "change": "flat"
      },
      {
        "symbol": "Bitcoin",
        "price": "70,719",
        "change": "+4.2%"
      },
      {
        "symbol": "Ethereum",
        "price": "2,140",
        "change": "+4.3%"
      },
      {
        "symbol": "USD Index",
        "price": "99.40",
        "change": "-0.2%"
      }
    ]
  },
  {
    "timestamp": "2026-03-20T16:00-04:00",
    "title": "Weekend Futures: Gold Hammered, Oil Surges on Iran Escalation",
    "commentary": "Gold crashes 3.3% to $4,497 as profit-taking accelerates after week's war premium fade\u2014silver plummets 6.6% in sympathy. Oil spikes 2% to $97.44 as Iran tensions flare again; WTI eyes $100 resistance. Equities close ugly: S&P -1.5%, Nasdaq -1.75% cap worst weekly rout since October '23. BTC +0.3% at $70,161 proves resilient hard-asset bid while everything else burns. Dollar grinds higher at 99.59 as global risk-off deepens.",
    "movers": [
      {
        "symbol": "Gold",
        "price": "4,497",
        "change": "-3.29%"
      },
      {
        "symbol": "Silver",
        "price": "67.99",
        "change": "-6.60%"
      },
      {
        "symbol": "Oil (WTI)",
        "price": "97.44",
        "change": "+1.98%"
      },
      {
        "symbol": "S&P 500",
        "price": "6,508",
        "change": "-1.49%"
      },
      {
        "symbol": "Nasdaq",
        "price": "23,929",
        "change": "-1.75%"
      },
      {
        "symbol": "Dow Jones",
        "price": "45,651",
        "change": "-0.80%"
      },
      {
        "symbol": "Bitcoin",
        "price": "70,161",
        "change": "+0.34%"
      },
      {
        "symbol": "Ethereum",
        "price": "2,132",
        "change": "-0.31%"
      },
      {
        "symbol": "USD Index",
        "price": "99.59",
        "change": "+0.36%"
      }
    ]
  }
]